{"availableResources":[{"id":1,"costNumb":"","costCenter":"","availablePeriods":[0,100000],"setup":[]},{"id":2,"costNumb":"","costCenter":"","availablePeriods":[0,100000],"setup":[]},{"id":3,"costNumb":"","costCenter":"","availablePeriods":[0,100000],"setup":[]},{"id":4,"costNumb":"","costCenter":"","availablePeriods":[0,100000],"setup":[]},{"id":5,"costNumb":"","costCenter":"","availablePeriods":[0,100000],"setup":[]},{"id":6,"costNumb":"","costCenter":"","availablePeriods":[0,100000],"setup":[]},{"id":7,"costNumb":"","costCenter":"","availablePeriods":[0,100000],"setup":[]}],"jobs":[{"idJob":1,"urgencyLevel":0,"releaseTime":0,"dueDate":0,"fixedStartingTime":0,"sucessorJobs":[],"operationsTopology":[{"idOp":1,"starting":true,"sucessorOperations":[2,5],"resources":[3,4,6],"time":[73,74,93],"transportation":[],"additionalTime":0,"fixedStartingTime":0,"overlappingCoeffiecient":1.0},{"idOp":2,"starting":false,"sucessorOperations":[3],"resources":[2,6,1],"time":[84,97,97],"transportation":[],"additionalTime":0,"fixedStartingTime":0,"overlappingCoeffiecient":1.0},{"idOp":3,"starting":false,"sucessorOperations":[4],"resources":[4,2,5],"time":[90,91,94],"transportation":[],"additionalTime":0,"fixedStartingTime":0,"overlappingCoeffiecient":1.0},{"idOp":4,"starting":false,"sucessorOperations":[],"resources":[5,7,2,6,1],"time":[15,33,26,26,36],"transportation":[],"additionalTime":0,"fixedStartingTime":0,"overlappingCoeffiecient":1.0},{"idOp":5,"starting":false,"sucessorOperations":[6],"resources":[7,5,4,6],"time":[16,16,47,17],"transportation":[],"additionalTime":0,"fixedStartingTime":0,"overlappingCoeffiecient":1.0},{"idOp":6,"starting":false,"sucessorOperations":[7],"resources":[4,2,5],"time":[41,99,74],"transportation":[],"additionalTime":0,"fixedStartingTime":0,"overlappingCoeffiecient":1.0},{"idOp":7,"starting":false,"sucessorOperations":[],"resources":[3,5,7,4],"time":[93,94,94,93],"transportation":[],"additionalTime":0,"fixedStartingTime":0,"overlappingCoeffiecient":1.0}]},{"idJob":2,"urgencyLevel":0,"releaseTime":0,"dueDate":0,"fixedStartingTime":0,"sucessorJobs":[],"operationsTopology":[{"idOp":1,"starting":true,"sucessorOperations":[2,5],"resources":[3,4,6],"time":[73,74,93],"transportation":[],"additionalTime":0,"fixedStartingTime":0,"overlappingCoeffiecient":1.0},{"idOp":2,"starting":false,"sucessorOperations":[3],"resources":[2,6,1],"time":[84,97,97],"transportation":[],"additionalTime":0,"fixedStartingTime":0,"overlappingCoeffiecient":1.0},{"idOp":3,"starting":false,"sucessorOperations":[4],"resources":[4,2,5],"time":[90,91,94],"transportation":[],"additionalTime":0,"fixedStartingTime":0,"overlappingCoeffiecient":1.0},{"idOp":4,"starting":false,"sucessorOperations":[],"resources":[5,7,2,6,1],"time":[15,33,26,26,36],"transportation":[],"additionalTime":0,"fixedStartingTime":0,"overlappingCoeffiecient":1.0},{"idOp":5,"starting":false,"sucessorOperations":[6],"resources":[7,5,4,6],"time":[16,16,47,17],"transportation":[],"additionalTime":0,"fixedStartingTime":0,"overlappingCoeffiecient":1.0},{"idOp":6,"starting":false,"sucessorOperations":[7],"resources":[4,2,5],"time":[41,99,74],"transportation":[],"additionalTime":0,"fixedStartingTime":0,"overlappingCoeffiecient":1.0},{"idOp":7,"starting":false,"sucessorOperations":[],"resources":[3,5,7,4],"time":[93,94,94,93],"transportation":[],"additionalTime":0,"fixedStartingTime":0,"overlappingCoeffiecient":1.0}]},{"idJob":3,"urgencyLevel":0,"releaseTime":0,"dueDate":0,"fixedStartingTime":0,"sucessorJobs":[],"operationsTopology":[{"idOp":1,"starting":false,"sucessorOperations":[2],"resources":[4,3,2,6],"time":[16,35,20,17],"transportation":[],"additionalTime":0,"fixedStartingTime":0,"overlappingCoeffiecient":1.0},{"idOp":2,"starting":false,"sucessorOperations":[3],"resources":[7,6,1],"time":[57,96,69],"transportation":[],"additionalTime":0,"fixedStartingTime":0,"overlappingCoeffiecient":1.0},{"idOp":3,"starting":false,"sucessorOperations":[4],"resources":[1,4,5],"time":[43,90,49],"transportation":[],"additionalTime":0,"fixedStartingTime":0,"overlappingCoeffiecient":1.0},{"idOp":4,"starting":false,"sucessorOperations":[5],"resources":[2,3,1,7,4],"time":[8,13,12,20,24],"transportation":[],"additionalTime":0,"fixedStartingTime":0,"overlappingCoeffiecient":1.0},{"idOp":5,"starting":false,"sucessorOperations":[16],"resources":[1,5,6,7],"time":[3,5,3,7],"transportation":[],"additionalTime":0,"fixedStartingTime":0,"overlappingCoeffiecient":1.0},{"idOp":6,"starting":false,"sucessorOperations":[7],"resources":[5,2,1],"time":[97,99,97],"transportation":[],"additionalTime":0,"fixedStartingTime":0,"overlappingCoeffiecient":1.0},{"idOp":7,"starting":false,"sucessorOperations":[8],"resources":[2,4,5,1,7],"time":[62,89,91,67,96],"transportation":[],"additionalTime":0,"fixedStartingTime":0,"overlappingCoeffiecient":1.0},{"idOp":8,"starting":false,"sucessorOperations":[9],"resources":[1,4,7],"time":[78,90,86],"transportation":[],"additionalTime":0,"fixedStartingTime":0,"overlappingCoeffiecient":1.0},{"idOp":9,"starting":false,"sucessorOperations":[10],"resources":[4,1,2],"time":[56,85,82],"transportation":[],"additionalTime":0,"fixedStartingTime":0,"overlappingCoeffiecient":1.0},{"idOp":10,"starting":false,"sucessorOperations":[16],"resources":[1,5,4,6,7],"time":[52,88,71,83,98],"transportation":[],"additionalTime":0,"fixedStartingTime":0,"overlappingCoeffiecient":1.0},{"idOp":11,"starting":false,"sucessorOperations":[12],"resources":[1,5,6,3,2],"time":[45,83,55,86,59],"transportation":[],"additionalTime":0,"fixedStartingTime":0,"overlappingCoeffiecient":1.0},{"idOp":12,"starting":false,"sucessorOperations":[13],"resources":[6,3,4],"time":[41,63,88],"transportation":[],"additionalTime":0,"fixedStartingTime":0,"overlappingCoeffiecient":1.0},{"idOp":13,"starting":false,"sucessorOperations":[14],"resources":[7,5,3,4],"time":[12,27,14,17],"transportation":[],"additionalTime":0,"fixedStartingTime":0,"overlappingCoeffiecient":1.0},{"idOp":14,"starting":false,"sucessorOperations":[15],"resources":[1,2,4,3],"time":[37,68,49,74],"transportation":[],"additionalTime":0,"fixedStartingTime":0,"overlappingCoeffiecient":1.0},{"idOp":15,"starting":false,"sucessorOperations":[16],"resources":[4,3,6,5,1],"time":[49,87,80,92,82],"transportation":[],"additionalTime":0,"fixedStartingTime":0,"overlappingCoeffiecient":1.0},{"idOp":16,"starting":false,"sucessorOperations":[17],"resources":[2,7,1,3],"time":[80,87,81,98],"transportation":[],"additionalTime":0,"fixedStartingTime":0,"overlappingCoeffiecient":1.0},{"idOp":17,"starting":false,"sucessorOperations":[],"resources":[7,1,3,4,5],"time":[9,20,25,20,9],"transportation":[],"additionalTime":0,"fixedStartingTime":0,"overlappingCoeffiecient":1.0}]},{"idJob":4,"urgencyLevel":0,"releaseTime":0,"dueDate":0,"fixedStartingTime":0,"sucessorJobs":[],"operationsTopology":[{"idOp":1,"starting":false,"sucessorOperations":[2],"resources":[1,3,7,4,5],"time":[32,35,37,61,58],"transportation":[],"additionalTime":0,"fixedStartingTime":0,"overlappingCoeffiecient":1.0},{"idOp":2,"starting":false,"sucessorOperations":[3,4,5],"resources":[4,3,1,5],"time":[80,98,88,91],"transportation":[],"additionalTime":0,"fixedStartingTime":0,"overlappingCoeffiecient":1.0},{"idOp":3,"starting":false,"sucessorOperations":[6],"resources":[7,1,5,6],"time":[85,95,99,93],"transportation":[],"additionalTime":0,"fixedStartingTime":0,"overlappingCoeffiecient":1.0},{"idOp":4,"starting":false,"sucessorOperations":[6],"resources":[2,1,7],"time":[79,83,80],"transportation":[],"additionalTime":0,"fixedStartingTime":0,"overlappingCoeffiecient":1.0},{"idOp":5,"starting":false,"sucessorOperations":[6],"resources":[4,2,7],"time":[84,91,89],"transportation":[],"additionalTime":0,"fixedStartingTime":0,"overlappingCoeffiecient":1.0},{"idOp":6,"starting":false,"sucessorOperations":[7],"resources":[7,5,4,6,1],"time":[74,88,89,76,75],"transportation":[],"additionalTime":0,"fixedStartingTime":0,"overlappingCoeffiecient":1.0},{"idOp":7,"starting":false,"sucessorOperations":[8],"resources":[5,6,4,2],"time":[67,95,92,82],"transportation":[],"additionalTime":0,"fixedStartingTime":0,"overlappingCoeffiecient":1.0},{"idOp":8,"starting":false,"sucessorOperations":[],"resources":[4,2,6],"time":[61,66,93],"transportation":[],"additionalTime":0,"fixedStartingTime":0,"overlappingCoeffiecient":1.0}]},{"idJob":5,"urgencyLevel":0,"releaseTime":0,"dueDate":0,"fixedStartingTime":0,"sucessorJobs":[],"operationsTopology":[{"idOp":1,"starting":false,"sucessorOperations":[2],"resources":[6,7,1],"time":[29,29,74],"transportation":[],"additionalTime":0,"fixedStartingTime":0,"overlappingCoeffiecient":1.0},{"idOp":2,"starting":false,"sucessorOperations":[3],"resources":[2,5,7,1],"time":[64,76,89,80],"transportation":[],"additionalTime":0,"fixedStartingTime":0,"overlappingCoeffiecient":1.0},{"idOp":3,"starting":false,"sucessorOperations":[4,6],"resources":[1,3,6],"time":[85,98,98],"transportation":[],"additionalTime":0,"fixedStartingTime":0,"overlappingCoeffiecient":1.0},{"idOp":4,"starting":false,"sucessorOperations":[5],"resources":[1,6,5,7],"time":[60,68,68,83],"transportation":[],"additionalTime":0,"fixedStartingTime":0,"overlappingCoeffiecient":1.0},{"idOp":5,"starting":false,"sucessorOperations":[],"resources":[1,2,3,4,5],"time":[82,86,86,96,98],"transportation":[],"additionalTime":0,"fixedStartingTime":0,"overlappingCoeffiecient":1.0},{"idOp":6,"starting":false,"sucessorOperations":[7],"resources":[7,1,3],"time":[90,99,90],"transportation":[],"additionalTime":0,"fixedStartingTime":0,"overlappingCoeffiecient":1.0},{"idOp":7,"starting":false,"sucessorOperations":[],"resources":[1,4,3,6,7],"time":[1,2,3,3,3],"transportation":[],"additionalTime":0,"fixedStartingTime":0,"overlappingCoeffiecient":1.0}]},{"idJob":6,"urgencyLevel":0,"releaseTime":0,"dueDate":0,"fixedStartingTime":0,"sucessorJobs":[],"operationsTopology":[{"idOp":1,"starting":false,"sucessorOperations":[2],"resources":[6,7,1],"time":[29,29,74],"transportation":[],"additionalTime":0,"fixedStartingTime":0,"overlappingCoeffiecient":1.0},{"idOp":2,"starting":false,"sucessorOperations":[3],"resources":[2,5,7,1],"time":[64,76,89,80],"transportation":[],"additionalTime":0,"fixedStartingTime":0,"overlappingCoeffiecient":1.0},{"idOp":3,"starting":false,"sucessorOperations":[4,6],"resources":[1,3,6],"time":[85,98,98],"transportation":[],"additionalTime":0,"fixedStartingTime":0,"overlappingCoeffiecient":1.0},{"idOp":4,"starting":false,"sucessorOperations":[5],"resources":[1,6,5,7],"time":[60,68,68,83],"transportation":[],"additionalTime":0,"fixedStartingTime":0,"overlappingCoeffiecient":1.0},{"idOp":5,"starting":false,"sucessorOperations":[],"resources":[1,2,3,4,5],"time":[82,86,86,96,98],"transportation":[],"additionalTime":0,"fixedStartingTime":0,"overlappingCoeffiecient":1.0},{"idOp":6,"starting":false,"sucessorOperations":[7],"resources":[7,1,3],"time":[90,99,90],"transportation":[],"additionalTime":0,"fixedStartingTime":0,"overlappingCoeffiecient":1.0},{"idOp":7,"starting":false,"sucessorOperations":[],"resources":[1,4,3,6,7],"time":[1,2,3,3,3],"transportation":[],"additionalTime":0,"fixedStartingTime":0,"overlappingCoeffiecient":1.0}]},{"idJob":7,"urgencyLevel":0,"releaseTime":0,"dueDate":0,"fixedStartingTime":0,"sucessorJobs":[],"operationsTopology":[{"idOp":1,"starting":false,"sucessorOperations":[2,6],"resources":[7,3,1,4],"time":[81,92,97,99],"transportation":[],"additionalTime":0,"fixedStartingTime":0,"overlappingCoeffiecient":1.0},{"idOp":2,"starting":false,"sucessorOperations":[3],"resources":[2,5,6,3,4],"time":[13,22,33,21,36],"transportation":[],"additionalTime":0,"fixedStartingTime":0,"overlappingCoeffiecient":1.0},{"idOp":3,"starting":false,"sucessorOperations":[4],"resources":[6,7,2],"time":[70,83,87],"transportation":[],"additionalTime":0,"fixedStartingTime":0,"overlappingCoeffiecient":1.0},{"idOp":4,"starting":false,"sucessorOperations":[5],"resources":[2,7,3,5,1],"time":[56,58,97,65,64],"transportation":[],"additionalTime":0,"fixedStartingTime":0,"overlappingCoeffiecient":1.0},{"idOp":5,"starting":false,"sucessorOperations":[],"resources":[1,3,6],"time":[35,58,41],"transportation":[],"additionalTime":0,"fixedStartingTime":0,"overlappingCoeffiecient":1.0},{"idOp":6,"starting":false,"sucessorOperations":[7],"resources":[6,3,1,7],"time":[60,79,95,77],"transportation":[],"additionalTime":0,"fixedStartingTime":0,"overlappingCoeffiecient":1.0},{"idOp":7,"starting":false,"sucessorOperations":[8],"resources":[5,4,7,2],"time":[68,79,88,96],"transportation":[],"additionalTime":0,"fixedStartingTime":0,"overlappingCoeffiecient":1.0},{"idOp":8,"starting":false,"sucessorOperations":[9],"resources":[6,3,2],"time":[53,89,91],"transportation":[],"additionalTime":0,"fixedStartingTime":0,"overlappingCoeffiecient":1.0},{"idOp":9,"starting":false,"sucessorOperations":[],"resources":[6,7,5],"time":[45,88,75],"transportation":[],"additionalTime":0,"fixedStartingTime":0,"overlappingCoeffiecient":1.0}]},{"idJob":8,"urgencyLevel":0,"releaseTime":0,"dueDate":0,"fixedStartingTime":0,"sucessorJobs":[],"operationsTopology":[{"idOp":1,"starting":false,"sucessorOperations":[2,6],"resources":[7,3,1,4],"time":[81,92,97,99],"transportation":[],"additionalTime":0,"fixedStartingTime":0,"overlappingCoeffiecient":1.0},{"idOp":2,"starting":false,"sucessorOperations":[3],"resources":[2,5,6,3,4],"time":[13,22,33,21,36],"transportation":[],"additionalTime":0,"fixedStartingTime":0,"overlappingCoeffiecient":1.0},{"idOp":3,"starting":false,"sucessorOperations":[4],"resources":[6,7,2],"time":[70,83,87],"transportation":[],"additionalTime":0,"fixedStartingTime":0,"overlappingCoeffiecient":1.0},{"idOp":4,"starting":false,"sucessorOperations":[5],"resources":[2,7,3,5,1],"time":[56,58,97,65,64],"transportation":[],"additionalTime":0,"fixedStartingTime":0,"overlappingCoeffiecient":1.0},{"idOp":5,"starting":false,"sucessorOperations":[],"resources":[1,3,6],"time":[35,58,41],"transportation":[],"additionalTime":0,"fixedStartingTime":0,"overlappingCoeffiecient":1.0},{"idOp":6,"starting":false,"sucessorOperations":[7],"resources":[6,3,1,7],"time":[60,79,95,77],"transportation":[],"additionalTime":0,"fixedStartingTime":0,"overlappingCoeffiecient":1.0},{"idOp":7,"starting":false,"sucessorOperations":[8],"resources":[5,4,7,2],"time":[68,79,88,96],"transportation":[],"additionalTime":0,"fixedStartingTime":0,"overlappingCoeffiecient":1.0},{"idOp":8,"starting":false,"sucessorOperations":[9],"resources":[6,3,2],"time":[53,89,91],"transportation":[],"additionalTime":0,"fixedStartingTime":0,"overlappingCoeffiecient":1.0},{"idOp":9,"starting":false,"sucessorOperations":[],"resources":[6,7,5],"time":[45,88,75],"transportation":[],"additionalTime":0,"fixedStartingTime":0,"overlappingCoeffiecient":1.0}]},{"idJob":9,"urgencyLevel":0,"releaseTime":0,"dueDate":0,"fixedStartingTime":0,"sucessorJobs":[],"operationsTopology":[{"idOp":1,"starting":false,"sucessorOperations":[2],"resources":[3,7,2,1,4],"time":[75,83,93,75,89],"transportation":[],"additionalTime":0,"fixedStartingTime":0,"overlappingCoeffiecient":1.0},{"idOp":2,"starting":false,"sucessorOperations":[3],"resources":[3,5,6,1],"time":[24,63,28,67],"transportation":[],"additionalTime":0,"fixedStartingTime":0,"overlappingCoeffiecient":1.0},{"idOp":3,"starting":false,"sucessorOperations":[10],"resources":[7,1,6],"time":[97,99,97],"transportation":[],"additionalTime":0,"fixedStartingTime":0,"overlappingCoeffiecient":1.0},{"idOp":4,"starting":false,"sucessorOperations":[5],"resources":[4,6,3,5,2],"time":[31,51,57,93,34],"transportation":[],"additionalTime":0,"fixedStartingTime":0,"overlappingCoeffiecient":1.0},{"idOp":5,"starting":false,"sucessorOperations":[6],"resources":[7,6,2],"time":[96,96,96],"transportation":[],"additionalTime":0,"fixedStartingTime":0,"overlappingCoeffiecient":1.0},{"idOp":6,"starting":false,"sucessorOperations":[10],"resources":[6,4,3],"time":[75,82,80],"transportation":[],"additionalTime":0,"fixedStartingTime":0,"overlappingCoeffiecient":1.0},{"idOp":7,"starting":false,"sucessorOperations":[8],"resources":[4,7,3],"time":[13,24,37],"transportation":[],"additionalTime":0,"fixedStartingTime":0,"overlappingCoeffiecient":1.0},{"idOp":8,"starting":false,"sucessorOperations":[9],"resources":[3,1,6,5],"time":[18,24,25,37],"transportation":[],"additionalTime":0,"fixedStartingTime":0,"overlappingCoeffiecient":1.0},{"idOp":9,"starting":false,"sucessorOperations":[10],"resources":[3,2,4,7,6],"time":[10,29,14,15,15],"transportation":[],"additionalTime":0,"fixedStartingTime":0,"overlappingCoeffiecient":1.0},{"idOp":10,"starting":false,"sucessorOperations":[11],"resources":[7,1,6,5],"time":[68,79,87,75],"transportation":[],"additionalTime":0,"fixedStartingTime":0,"overlappingCoeffiecient":1.0},{"idOp":11,"starting":false,"sucessorOperations":[12],"resources":[2,4,7,1],"time":[34,60,46,62],"transportation":[],"additionalTime":0,"fixedStartingTime":0,"overlappingCoeffiecient":1.0},{"idOp":12,"starting":false,"sucessorOperations":[13],"resources":[4,6,7,2,1],"time":[8,12,16,8,19],"transportation":[],"additionalTime":0,"fixedStartingTime":0,"overlappingCoeffiecient":1.0},{"idOp":13,"starting":false,"sucessorOperations":[],"resources":[5,7,1],"time":[1,1,3],"transportation":[],"additionalTime":0,"fixedStartingTime":0,"overlappingCoeffiecient":1.0}]},{"idJob":10,"urgencyLevel":0,"releaseTime":0,"dueDate":0,"fixedStartingTime":0,"sucessorJobs":[],"operationsTopology":[{"idOp":1,"starting":false,"sucessorOperations":[2],"resources":[3,2,7],"time":[11,28,15],"transportation":[],"additionalTime":0,"fixedStartingTime":0,"overlappingCoeffiecient":1.0},{"idOp":2,"starting":false,"sucessorOperations":[3],"resources":[7,1,5,4,6],"time":[88,90,91,95,88],"transportation":[],"additionalTime":0,"fixedStartingTime":0,"overlappingCoeffiecient":1.0},{"idOp":3,"starting":false,"sucessorOperations":[4],"resources":[3,4,6,7,1],"time":[13,20,17,17,21],"transportation":[],"additionalTime":0,"fixedStartingTime":0,"overlappingCoeffiecient":1.0},{"idOp":4,"starting":false,"sucessorOperations":[5,7,9],"resources":[1,5,6],"time":[12,34,34],"transportation":[],"additionalTime":0,"fixedStartingTime":0,"overlappingCoeffiecient":1.0},{"idOp":5,"starting":false,"sucessorOperations":[6],"resources":[5,1,3,7,6],"time":[41,44,85,80,50],"transportation":[],"additionalTime":0,"fixedStartingTime":0,"overlappingCoeffiecient":1.0},{"idOp":6,"starting":false,"sucessorOperations":[],"resources":[4,1,3,7],"time":[4,10,9,8],"transportation":[],"additionalTime":0,"fixedStartingTime":0,"overlappingCoeffiecient":1.0},{"idOp":7,"starting":false,"sucessorOperations":[8],"resources":[1,4,7,6,2],"time":[27,75,41,65,71],"transportation":[],"additionalTime":0,"fixedStartingTime":0,"overlappingCoeffiecient":1.0},{"idOp":8,"starting":false,"sucessorOperations":[],"resources":[7,2,6],"time":[40,90,47],"transportation":[],"additionalTime":0,"fixedStartingTime":0,"overlappingCoeffiecient":1.0},{"idOp":9,"starting":false,"sucessorOperations":[10],"resources":[4,6,1,3,2],"time":[8,11,9,22,19],"transportation":[],"additionalTime":0,"fixedStartingTime":0,"overlappingCoeffiecient":1.0},{"idOp":10,"starting":false,"sucessorOperations":[],"resources":[5,4,7,2],"time":[23,50,24,45],"transportation":[],"additionalTime":0,"fixedStartingTime":0,"overlappingCoeffiecient":1.0}]},{"idJob":11,"urgencyLevel":0,"releaseTime":0,"dueDate":0,"fixedStartingTime":0,"sucessorJobs":[],"operationsTopology":[{"idOp":1,"starting":false,"sucessorOperations":[2],"resources":[3,2,7],"time":[11,28,15],"transportation":[],"additionalTime":0,"fixedStartingTime":0,"overlappingCoeffiecient":1.0},{"idOp":2,"starting":false,"sucessorOperations":[3],"resources":[7,1,5,4,6],"time":[88,90,91,95,88],"transportation":[],"additionalTime":0,"fixedStartingTime":0,"overlappingCoeffiecient":1.0},{"idOp":3,"starting":false,"sucessorOperations":[4],"resources":[3,4,6,7,1],"time":[13,20,17,17,21],"transportation":[],"additionalTime":0,"fixedStartingTime":0,"overlappingCoeffiecient":1.0},{"idOp":4,"starting":false,"sucessorOperations":[5,7,9],"resources":[1,5,6],"time":[12,34,34],"transportation":[],"additionalTime":0,"fixedStartingTime":0,"overlappingCoeffiecient":1.0},{"idOp":5,"starting":false,"sucessorOperations":[6],"resources":[5,1,3,7,6],"time":[41,44,85,80,50],"transportation":[],"additionalTime":0,"fixedStartingTime":0,"overlappingCoeffiecient":1.0},{"idOp":6,"starting":false,"sucessorOperations":[],"resources":[4,1,3,7],"time":[4,10,9,8],"transportation":[],"additionalTime":0,"fixedStartingTime":0,"overlappingCoeffiecient":1.0},{"idOp":7,"starting":false,"sucessorOperations":[8],"resources":[1,4,7,6,2],"time":[27,75,41,65,71],"transportation":[],"additionalTime":0,"fixedStartingTime":0,"overlappingCoeffiecient":1.0},{"idOp":8,"starting":false,"sucessorOperations":[],"resources":[7,2,6],"time":[40,90,47],"transportation":[],"additionalTime":0,"fixedStartingTime":0,"overlappingCoeffiecient":1.0},{"idOp":9,"starting":false,"sucessorOperations":[10],"resources":[4,6,1,3,2],"time":[8,11,9,22,19],"transportation":[],"additionalTime":0,"fixedStartingTime":0,"overlappingCoeffiecient":1.0},{"idOp":10,"starting":false,"sucessorOperations":[],"resources":[5,4,7,2],"time":[23,50,24,45],"transportation":[],"additionalTime":0,"fixedStartingTime":0,"overlappingCoeffiecient":1.0}]},{"idJob":12,"urgencyLevel":0,"releaseTime":0,"dueDate":0,"fixedStartingTime":0,"sucessorJobs":[],"operationsTopology":[{"idOp":1,"starting":false,"sucessorOperations":[2],"resources":[3,2,7],"time":[11,28,15],"transportation":[],"additionalTime":0,"fixedStartingTime":0,"overlappingCoeffiecient":1.0},{"idOp":2,"starting":false,"sucessorOperations":[3],"resources":[7,1,5,4,6],"time":[88,90,91,95,88],"transportation":[],"additionalTime":0,"fixedStartingTime":0,"overlappingCoeffiecient":1.0},{"idOp":3,"starting":false,"sucessorOperations":[4],"resources":[3,4,6,7,1],"time":[13,20,17,17,21],"transportation":[],"additionalTime":0,"fixedStartingTime":0,"overlappingCoeffiecient":1.0},{"idOp":4,"starting":false,"sucessorOperations":[5,7,9],"resources":[1,5,6],"time":[12,34,34],"transportation":[],"additionalTime":0,"fixedStartingTime":0,"overlappingCoeffiecient":1.0},{"idOp":5,"starting":false,"sucessorOperations":[6],"resources":[5,1,3,7,6],"time":[41,44,85,80,50],"transportation":[],"additionalTime":0,"fixedStartingTime":0,"overlappingCoeffiecient":1.0},{"idOp":6,"starting":false,"sucessorOperations":[],"resources":[4,1,3,7],"time":[4,10,9,8],"transportation":[],"additionalTime":0,"fixedStartingTime":0,"overlappingCoeffiecient":1.0},{"idOp":7,"starting":false,"sucessorOperations":[8],"resources":[1,4,7,6,2],"time":[27,75,41,65,71],"transportation":[],"additionalTime":0,"fixedStartingTime":0,"overlappingCoeffiecient":1.0},{"idOp":8,"starting":false,"sucessorOperations":[],"resources":[7,2,6],"time":[40,90,47],"transportation":[],"additionalTime":0,"fixedStartingTime":0,"overlappingCoeffiecient":1.0},{"idOp":9,"starting":false,"sucessorOperations":[10],"resources":[4,6,1,3,2],"time":[8,11,9,22,19],"transportation":[],"additionalTime":0,"fixedStartingTime":0,"overlappingCoeffiecient":1.0},{"idOp":10,"starting":false,"sucessorOperations":[],"resources":[5,4,7,2],"time":[23,50,24,45],"transportation":[],"additionalTime":0,"fixedStartingTime":0,"overlappingCoeffiecient":1.0}]},{"idJob":13,"urgencyLevel":0,"releaseTime":0,"dueDate":0,"fixedStartingTime":0,"sucessorJobs":[],"operationsTopology":[{"idOp":1,"starting":false,"sucessorOperations":[2],"resources":[3,1,7,5,2],"time":[32,46,38,80,93],"transportation":[],"additionalTime":0,"fixedStartingTime":0,"overlappingCoeffiecient":1.0},{"idOp":2,"starting":false,"sucessorOperations":[3,4,5],"resources":[5,4,2],"time":[51,94,79],"transportation":[],"additionalTime":0,"fixedStartingTime":0,"overlappingCoeffiecient":1.0},{"idOp":3,"starting":false,"sucessorOperations":[6],"resources":[1,6,2,3,5],"time":[90,95,90,95,92],"transportation":[],"additionalTime":0,"fixedStartingTime":0,"overlappingCoeffiecient":1.0},{"idOp":4,"starting":false,"sucessorOperations":[6],"resources":[2,6,4,3],"time":[98,99,98,98],"transportation":[],"additionalTime":0,"fixedStartingTime":0,"overlappingCoeffiecient":1.0},{"idOp":5,"starting":false,"sucessorOperations":[6],"resources":[1,2,6,4,7],"time":[13,29,26,14,34],"transportation":[],"additionalTime":0,"fixedStartingTime":0,"overlappingCoeffiecient":1.0},{"idOp":6,"starting":false,"sucessorOperations":[7],"resources":[6,4,5],"time":[77,93,83],"transportation":[],"additionalTime":0,"fixedStartingTime":0,"overlappingCoeffiecient":1.0},{"idOp":7,"starting":false,"sucessorOperations":[8],"resources":[1,2,7,4],"time":[5,13,10,11],"transportation":[],"additionalTime":0,"fixedStartingTime":0,"overlappingCoeffiecient":1.0},{"idOp":8,"starting":false,"sucessorOperations":[],"resources":[2,6,5,3],"time":[78,80,83,87],"transportation":[],"additionalTime":0,"fixedStartingTime":0,"overlappingCoeffiecient":1.0}]},{"idJob":14,"urgencyLevel":0,"releaseTime":0,"dueDate":0,"fixedStartingTime":0,"sucessorJobs":[],"operationsTopology":[{"idOp":1,"starting":false,"sucessorOperations":[2],"resources":[6,3,2,4,7],"time":[14,22,21,32,22],"transportation":[],"additionalTime":0,"fixedStartingTime":0,"overlappingCoeffiecient":1.0},{"idOp":2,"starting":false,"sucessorOperations":[3],"resources":[3,7,4,5],"time":[54,81,67,72],"transportation":[],"additionalTime":0,"fixedStartingTime":0,"overlappingCoeffiecient":1.0},{"idOp":3,"starting":false,"sucessorOperations":[4,5],"resources":[2,5,3],"time":[10,10,16],"transportation":[],"additionalTime":0,"fixedStartingTime":0,"overlappingCoeffiecient":1.0},{"idOp":4,"starting":false,"sucessorOperations":[6],"resources":[1,2,5,7,3],"time":[5,13,10,11,13],"transportation":[],"additionalTime":0,"fixedStartingTime":0,"overlappingCoeffiecient":1.0},{"idOp":5,"starting":false,"sucessorOperations":[6],"resources":[5,1,6,7,4],"time":[58,75,61,64,68],"transportation":[],"additionalTime":0,"fixedStartingTime":0,"overlappingCoeffiecient":1.0},{"idOp":6,"starting":false,"sucessorOperations":[7],"resources":[4,1,3],"time":[96,96,96],"transportation":[],"additionalTime":0,"fixedStartingTime":0,"overlappingCoeffiecient":1.0},{"idOp":7,"starting":false,"sucessorOperations":[],"resources":[6,2,1],"time":[23,44,33],"transportation":[],"additionalTime":0,"fixedStartingTime":0,"overlappingCoeffiecient":1.0}]},{"idJob":15,"urgencyLevel":0,"releaseTime":0,"dueDate":0,"fixedStartingTime":0,"sucessorJobs":[],"operationsTopology":[{"idOp":1,"starting":false,"sucessorOperations":[2],"resources":[2,3,4],"time":[70,99,87],"transportation":[],"additionalTime":0,"fixedStartingTime":0,"overlappingCoeffiecient":1.0},{"idOp":2,"starting":false,"sucessorOperations":[5],"resources":[6,2,1,7],"time":[93,94,97,95],"transportation":[],"additionalTime":0,"fixedStartingTime":0,"overlappingCoeffiecient":1.0},{"idOp":3,"starting":false,"sucessorOperations":[4],"resources":[5,4,2,7,3],"time":[81,91,85,86,93],"transportation":[],"additionalTime":0,"fixedStartingTime":0,"overlappingCoeffiecient":1.0},{"idOp":4,"starting":false,"sucessorOperations":[5],"resources":[6,7,3],"time":[21,33,53],"transportation":[],"additionalTime":0,"fixedStartingTime":0,"overlappingCoeffiecient":1.0},{"idOp":5,"starting":false,"sucessorOperations":[6],"resources":[5,3,6,4],"time":[80,81,81,96],"transportation":[],"additionalTime":0,"fixedStartingTime":0,"overlappingCoeffiecient":1.0},{"idOp":6,"starting":false,"sucessorOperations":[],"resources":[7,5,4],"time":[92,97,95],"transportation":[],"additionalTime":0,"fixedStartingTime":0,"overlappingCoeffiecient":1.0}]}]}